{
    "name": "Lúcifer Theme",
    "description": "Um tema sombrio e elegante com vermelho vibrante, preto profundo e detalhes em branco.",
    "authors": [
        {
            "name": "Pl4nk Stan | +44",
            "id": "466968658997149706"
        }
    ],
    "semanticColors": {
        "BACKGROUND_PRIMARY": ["#000000", "#000000", "#000000"],
        "BACKGROUND_SECONDARY": ["#0d0d0d", "#0d0d0d", "#0d0d0d"],
        "BACKGROUND_TERTIARY": ["#1a1a1a", "#1a1a1a", "#1a1a1a"],
        "BACKGROUND_ACCENT": ["#330000", "#330000", "#330000"],
        "BACKGROUND_FLOATING": ["#1a0000", "#1a0000", "#1a0000"],

        "BACKGROUND_MODIFIER_HOVER": ["#ff000026", "#ff000026", "#ff000026"],
        "BACKGROUND_MODIFIER_ACTIVE": ["#ff00004d", "#ff00004d", "#ff00004d"],
        "BACKGROUND_MODIFIER_SELECTED": ["#ff000099", "#ff000099", "#ff000099"],

        "TEXT_NORMAL": ["#ff1a1a", "#ff1a1a", "#ff1a1a"],
        "TEXT_MUTED": ["#b30000", "#b30000", "#b30000"],
        "TEXT_LINK": ["#ff3333", "#ff3333", "#ff3333"],
        "TEXT_POSITIVE": ["#ff4d4d", "#ff4d4d", "#ff4d4d"],
        "TEXT_WARNING": ["#ff6666", "#ff6666", "#ff6666"],
        "TEXT_DANGER": ["#ff0000", "#ff0000", "#ff0000"],

        "HEADER_PRIMARY": ["#ffffff", "#ffffff", "#ffffff"],
        "HEADER_SECONDARY": ["#ff1a1a", "#ff1a1a", "#ff1a1a"],

        "INTERACTIVE_NORMAL": ["#ffffff", "#ffffff", "#ffffff"],
        "INTERACTIVE_HOVER": ["#ff0000", "#ff0000", "#ff0000"],
        "INTERACTIVE_ACTIVE": ["#b30000", "#b30000", "#b30000"],
        "INTERACTIVE_MUTED": ["#4d0000", "#4d0000", "#4d0000"],

        "CHANNELS_DEFAULT": ["#ffffff", "#ffffff", "#ffffff"],
        "CHANNEL_ICON": ["#ff00004d", "#ff00004d", "#ff00004d"],
        "CHANNEL_TEXT_AREA_PLACEHOLDER": ["#ff4d4d", "#ff4d4d", "#ff4d4d"],

        "SCROLLBAR_AUTO_THUMB": ["#ff0000", "#ff0000", "#ff0000"],
        "SCROLLBAR_AUTO_TRACK": ["#1a1a1a", "#1a1a1a", "#1a1a1a"],
        "SCROLLBAR_THIN_THUMB": ["#ff0000", "#ff0000", "#ff0000"],
        "SCROLLBAR_THIN_TRACK": ["#1a1a1a", "#1a1a1a", "#1a1a1a"],

        "MENTION_FOREGROUND": ["#ffffff", "#ffffff", "#ffffff"],
        "BACKGROUND_MENTIONED": ["#ff00001a", "#ff00001a", "#ff00001a"],
        "BACKGROUND_MENTIONED_HOVER": ["#ff000033", "#ff000033", "#ff000033"],

        "CARD_PRIMARY_BG": ["#0d0d0d", "#0d0d0d", "#0d0d0d"],
        "CARD_SECONDARY_BG": ["#000000", "#000000", "#000000"],
        "PANEL_BG": ["#0d0d0d", "#0d0d0d", "#0d0d0d"]
    },
    "rawColors": {
        "PRIMARY_100": "#ff1a1a",
        "PRIMARY_200": "#ff3333",
        "PRIMARY_300": "#ff4d4d",
        "PRIMARY_400": "#ff6666",
        "PRIMARY_500": "#b30000",
        "BLACK_500": "#000000",
        "WHITE_500": "#ffffff",
        "RED_400": "#ff0000",
        "GREEN_360": "#b30000",
        "YELLOW_300": "#ff3333",
        "PLUM_20": "#0d0d0d",
        "PLUM_16": "#000000",
        "PLUM_22": "#1a1a1a"
    },
    "background": {
        "url": "https://media1.tenor.com/m/xLGEuv3RXQkAAAAd/skull-emoji-skeletons.gif",
        "alpha": 1
    },
    "plus": {
        "version": 0,
        "customOverlays": true,
        "icons": {
            "ic_mic_neutral": "#ffffff",
            "ic_mic_muted_neutral": "#ff0000",
            "ic_soundboard": "#ffffff",
            "ic_soundboard_muted": "#ff0000",
            "ic_video": "#ffffff",
            "ic_video_disabled": "#ff0000"
        },
        "iconpack": "rosiecord-plumpy"
    },
    "spec": 2
}
